{"municipio":"Peruíbe","anos":{"2020":null,"2021":[{"funcao":"SAÚDE","empenhado":105474039.96,"liquidado":90874206.64,"pago":82625952.87,"pct_liquidado":86.2,"pct_pago":78.3},{"funcao":"EDUCAÇÃO","empenhado":100170725.62,"liquidado":81811916.9,"pago":62535910.85,"pct_liquidado":81.7,"pct_pago":62.4},{"funcao":"ADMINISTRAÇÃO","empenhado":78228941.65,"liquidado":47354689.6,"pago":44072045.77,"pct_liquidado":60.5,"pct_pago":56.3},{"funcao":"URBANISMO","empenhado":69246631.76,"liquidado":46423438.7,"pago":33494169.52,"pct_liquidado":67.0,"pct_pago":48.4},{"funcao":"PREVIDÊNCIA SOCIAL","empenhado":22708348.64,"liquidado":22628280.12,"pago":22582518.37,"pct_liquidado":99.6,"pct_pago":99.4},{"funcao":"ENCARGOS ESPECIAIS","empenhado":15910243.56,"liquidado":13071637.82,"pago":13056865.33,"pct_liquidado":82.2,"pct_pago":82.1},{"funcao":"LEGISLATIVA","empenhado":7927259.62,"liquidado":7518291.78,"pago":7517871.78,"pct_liquidado":94.8,"pct_pago":94.8},{"funcao":"ASSISTÊNCIA SOCIAL","empenhado":7684898.01,"liquidado":7086469.02,"pago":6761427.41,"pct_liquidado":92.2,"pct_pago":88.0},{"funcao":"HABITAÇÃO","empenhado":5860574.76,"liquidado":800911.86,"pago":799238.54,"pct_liquidado":13.7,"pct_pago":13.6},{"funcao":"COMÉRCIO E SERVIÇOS","empenhado":4568225.11,"liquidado":3513161.65,"pago":3473118.28,"pct_liquidado":76.9,"pct_pago":76.0},{"funcao":"SANEAMENTO","empenhado":2512540.82,"liquidado":2512540.76,"pago":2512540.76,"pct_liquidado":100.0,"pct_pago":100.0},{"funcao":"DESPORTO E LAZER","empenhado":2392509.68,"liquidado":2158974.62,"pago":1955544.76,"pct_liquidado":90.2,"pct_pago":81.7},{"funcao":"SEGURANÇA PÚBLICA","empenhado":2331315.46,"liquidado":2016239.16,"pago":1575940.51,"pct_liquidado":86.5,"pct_pago":67.6},{"funcao":"CULTURA","empenhado":1437294.18,"liquidado":1322244.29,"pago":1226012.07,"pct_liquidado":92.0,"pct_pago":85.3},{"funcao":"AGRICULTURA","empenhado":1059061.93,"liquidado":395545.93,"pago":393065.93,"pct_liquidado":37.3,"pct_pago":37.1},{"funcao":"GESTÃO AMBIENTAL","empenhado":624445.13,"liquidado":590289.27,"pago":574911.64,"pct_liquidado":94.5,"pct_pago":92.1}],"2022":[{"funcao":"EDUCAÇÃO","empenhado":182337379.63,"liquidado":112596904.67,"pago":104808268.19,"pct_liquidado":61.8,"pct_pago":57.5},{"funcao":"SAÚDE","empenhado":136308063.33,"liquidado":104058680.16,"pago":95274509.2,"pct_liquidado":76.3,"pct_pago":69.9},{"funcao":"URBANISMO","empenhado":118907209.42,"liquidado":56700997.92,"pago":48211939.05,"pct_liquidado":47.7,"pct_pago":40.5},{"funcao":"ADMINISTRAÇÃO","empenhado":70548262.14,"liquidado":60174810.32,"pago":56456455.83,"pct_liquidado":85.3,"pct_pago":80.0},{"funcao":"PREVIDÊNCIA SOCIAL","empenhado":27688566.6,"liquidado":27620171.0,"pago":27553462.71,"pct_liquidado":99.8,"pct_pago":99.5},{"funcao":"COMÉRCIO E SERVIÇOS","empenhado":14236287.96,"liquidado":7089564.85,"pago":6893005.73,"pct_liquidado":49.8,"pct_pago":48.4},{"funcao":"ASSISTÊNCIA SOCIAL","empenhado":10032032.42,"liquidado":9501071.71,"pago":8964912.61,"pct_liquidado":94.7,"pct_pago":89.4},{"funcao":"LEGISLATIVA","empenhado":9605410.78,"liquidado":8783735.54,"pago":8783735.54,"pct_liquidado":91.4,"pct_pago":91.4},{"funcao":"SEGURANÇA PÚBLICA","empenhado":7639754.51,"liquidado":6690787.91,"pago":6280053.21,"pct_liquidado":87.6,"pct_pago":82.2},{"funcao":"DESPORTO E LAZER","empenhado":2657950.92,"liquidado":2580900.74,"pago":2538885.27,"pct_liquidado":97.1,"pct_pago":95.5},{"funcao":"CULTURA","empenhado":2309032.01,"liquidado":1824425.87,"pago":1723967.34,"pct_liquidado":79.0,"pct_pago":74.7},{"funcao":"HABITAÇÃO","empenhado":1880548.58,"liquidado":1162312.12,"pago":1155612.65,"pct_liquidado":61.8,"pct_pago":61.5},{"funcao":"GESTÃO AMBIENTAL","empenhado":1291088.91,"liquidado":1246517.31,"pago":1081347.57,"pct_liquidado":96.5,"pct_pago":83.8},{"funcao":"AGRICULTURA","empenhado":563907.12,"liquidado":495714.22,"pago":449649.5,"pct_liquidado":87.9,"pct_pago":79.7},{"funcao":"ENCARGOS ESPECIAIS","empenhado":2336.07,"liquidado":2336.07,"pago":2336.07,"pct_liquidado":100.0,"pct_pago":100.0}],"2023":[{"funcao":"EDUCAÇÃO","empenhado":197227945.73,"liquidado":125243146.93,"pago":116630126.53,"pct_liquidado":63.5,"pct_pago":59.1},{"funcao":"URBANISMO","empenhado":170118483.75,"liquidado":69736719.48,"pago":53352946.62,"pct_liquidado":41.0,"pct_pago":31.4},{"funcao":"SAÚDE","empenhado":155916792.65,"liquidado":116912821.66,"pago":100668067.99,"pct_liquidado":75.0,"pct_pago":64.6},{"funcao":"ADMINISTRAÇÃO","empenhado":72584784.93,"liquidado":68734905.03,"pago":60588795.33,"pct_liquidado":94.7,"pct_pago":83.5},{"funcao":"PREVIDÊNCIA SOCIAL","empenhado":31822907.55,"liquidado":31662528.26,"pago":31626709.42,"pct_liquidado":99.5,"pct_pago":99.4},{"funcao":"COMÉRCIO E SERVIÇOS","empenhado":17816867.03,"liquidado":10212194.25,"pago":9238906.25,"pct_liquidado":57.3,"pct_pago":51.9},{"funcao":"ASSISTÊNCIA SOCIAL","empenhado":13022103.85,"liquidado":10699271.04,"pago":9700059.02,"pct_liquidado":82.2,"pct_pago":74.5},{"funcao":"LEGISLATIVA","empenhado":10309994.77,"liquidado":9974296.14,"pago":9974296.14,"pct_liquidado":96.7,"pct_pago":96.7},{"funcao":"SEGURANÇA PÚBLICA","empenhado":9303242.62,"liquidado":7966875.0,"pago":6197629.41,"pct_liquidado":85.6,"pct_pago":66.6},{"funcao":"HABITAÇÃO","empenhado":3290087.36,"liquidado":2615759.86,"pago":2606213.32,"pct_liquidado":79.5,"pct_pago":79.2},{"funcao":"CULTURA","empenhado":3083210.95,"liquidado":2546394.99,"pago":2352845.38,"pct_liquidado":82.6,"pct_pago":76.3},{"funcao":"DESPORTO E LAZER","empenhado":3033166.55,"liquidado":2883055.29,"pago":2827179.24,"pct_liquidado":95.1,"pct_pago":93.2},{"funcao":"GESTÃO AMBIENTAL","empenhado":2348372.84,"liquidado":2129289.02,"pago":1871021.04,"pct_liquidado":90.7,"pct_pago":79.7},{"funcao":"AGRICULTURA","empenhado":782654.5,"liquidado":719881.72,"pago":670909.18,"pct_liquidado":92.0,"pct_pago":85.7}],"2024":[{"funcao":"EDUCAÇÃO","empenhado":159674920.25,"liquidado":130363776.57,"pago":122549351.6,"pct_liquidado":81.6,"pct_pago":76.7},{"funcao":"SAÚDE","empenhado":154555998.83,"liquidado":127401279.72,"pago":119319270.32,"pct_liquidado":82.4,"pct_pago":77.2},{"funcao":"URBANISMO","empenhado":152544796.35,"liquidado":84386820.27,"pago":59541584.27,"pct_liquidado":55.3,"pct_pago":39.0},{"funcao":"ADMINISTRAÇÃO","empenhado":85887042.64,"liquidado":72864244.78,"pago":69537241.02,"pct_liquidado":84.8,"pct_pago":81.0},{"funcao":"PREVIDÊNCIA SOCIAL","empenhado":35341730.53,"liquidado":35160757.07,"pago":35160757.07,"pct_liquidado":99.5,"pct_pago":99.5},{"funcao":"COMÉRCIO E SERVIÇOS","empenhado":26676778.78,"liquidado":11734955.19,"pago":10303618.73,"pct_liquidado":44.0,"pct_pago":38.6},{"funcao":"ASSISTÊNCIA SOCIAL","empenhado":11923810.0,"liquidado":11082910.91,"pago":10463755.23,"pct_liquidado":92.9,"pct_pago":87.8},{"funcao":"LEGISLATIVA","empenhado":11556081.56,"liquidado":10971504.16,"pago":10971504.16,"pct_liquidado":94.9,"pct_pago":94.9},{"funcao":"SEGURANÇA PÚBLICA","empenhado":9289003.19,"liquidado":8942255.7,"pago":7447276.58,"pct_liquidado":96.3,"pct_pago":80.2},{"funcao":"DESPORTO E LAZER","empenhado":5064727.84,"liquidado":3093992.91,"pago":3067429.48,"pct_liquidado":61.1,"pct_pago":60.6},{"funcao":"CULTURA","empenhado":3400072.17,"liquidado":2384246.45,"pago":1968361.38,"pct_liquidado":70.1,"pct_pago":57.9},{"funcao":"GESTÃO AMBIENTAL","empenhado":1799556.62,"liquidado":1718722.82,"pago":1645945.2,"pct_liquidado":95.5,"pct_pago":91.5},{"funcao":"HABITAÇÃO","empenhado":1608736.02,"liquidado":1597704.06,"pago":1592027.62,"pct_liquidado":99.3,"pct_pago":99.0},{"funcao":"AGRICULTURA","empenhado":400775.02,"liquidado":381200.41,"pago":366980.41,"pct_liquidado":95.1,"pct_pago":91.6}],"2025":[{"funcao":"EDUCAÇÃO","empenhado":181965753.32,"liquidado":139900896.52,"pago":133705191.59,"pct_liquidado":76.9,"pct_pago":73.5},{"funcao":"SAÚDE","empenhado":133701566.63,"liquidado":118075017.65,"pago":110314812.25,"pct_liquidado":88.3,"pct_pago":82.5},{"funcao":"URBANISMO","empenhado":111797749.21,"liquidado":58795855.23,"pago":32153728.45,"pct_liquidado":52.6,"pct_pago":28.8},{"funcao":"ADMINISTRAÇÃO","empenhado":89368867.56,"liquidado":82091467.86,"pago":77259630.75,"pct_liquidado":91.9,"pct_pago":86.5},{"funcao":"PREVIDÊNCIA SOCIAL","empenhado":40071004.99,"liquidado":39957098.8,"pago":39952206.0,"pct_liquidado":99.7,"pct_pago":99.7},{"funcao":"COMÉRCIO E SERVIÇOS","empenhado":23510003.45,"liquidado":14789523.64,"pago":14534226.49,"pct_liquidado":62.9,"pct_pago":61.8},{"funcao":"ASSISTÊNCIA SOCIAL","empenhado":12807621.38,"liquidado":11500772.02,"pago":11077853.85,"pct_liquidado":89.8,"pct_pago":86.5},{"funcao":"LEGISLATIVA","empenhado":12497234.67,"liquidado":11861680.88,"pago":11841212.3,"pct_liquidado":94.9,"pct_pago":94.8},{"funcao":"SEGURANÇA PÚBLICA","empenhado":11632074.48,"liquidado":10695617.62,"pago":9571934.13,"pct_liquidado":91.9,"pct_pago":82.3},{"funcao":"DESPORTO E LAZER","empenhado":3992662.22,"liquidado":3664970.96,"pago":3632093.76,"pct_liquidado":91.8,"pct_pago":91.0},{"funcao":"CULTURA","empenhado":3661055.93,"liquidado":2650635.89,"pago":2592140.91,"pct_liquidado":72.4,"pct_pago":70.8},{"funcao":"GESTÃO AMBIENTAL","empenhado":2231551.38,"liquidado":2196949.14,"pago":2109395.56,"pct_liquidado":98.4,"pct_pago":94.5},{"funcao":"HABITAÇÃO","empenhado":1118126.75,"liquidado":1005027.12,"pago":998647.97,"pct_liquidado":89.9,"pct_pago":89.3},{"funcao":"AGRICULTURA","empenhado":536423.33,"liquidado":503293.98,"pago":448676.21,"pct_liquidado":93.8,"pct_pago":83.6}],"2026":[{"funcao":"URBANISMO","empenhado":62178050.77,"liquidado":19064776.15,"pago":9791244.63,"pct_liquidado":30.7,"pct_pago":15.7},{"funcao":"ADMINISTRAÇÃO","empenhado":58168298.28,"liquidado":15283457.69,"pago":11910866.78,"pct_liquidado":26.3,"pct_pago":20.5},{"funcao":"EDUCAÇÃO","empenhado":54682090.51,"liquidado":37958076.29,"pago":29813472.92,"pct_liquidado":69.4,"pct_pago":54.5},{"funcao":"SAÚDE","empenhado":49427702.58,"liquidado":37126075.68,"pago":27182951.3,"pct_liquidado":75.1,"pct_pago":55.0},{"funcao":"PREVIDÊNCIA SOCIAL","empenhado":13083615.33,"liquidado":12681719.44,"pago":12681719.44,"pct_liquidado":96.9,"pct_pago":96.9},{"funcao":"COMÉRCIO E SERVIÇOS","empenhado":9929537.16,"liquidado":7324927.39,"pago":6924547.05,"pct_liquidado":73.8,"pct_pago":69.7},{"funcao":"ASSISTÊNCIA SOCIAL","empenhado":9459881.27,"liquidado":4951931.49,"pago":4264765.65,"pct_liquidado":52.3,"pct_pago":45.1},{"funcao":"ENCARGOS ESPECIAIS","empenhado":9143018.0,"liquidado":6001750.88,"pago":6001750.88,"pct_liquidado":65.6,"pct_pago":65.6},{"funcao":"LEGISLATIVA","empenhado":7056291.87,"liquidado":3731072.6,"pago":3731072.6,"pct_liquidado":52.9,"pct_pago":52.9},{"funcao":"SEGURANÇA PÚBLICA","empenhado":5619986.47,"liquidado":4524876.78,"pago":3272478.38,"pct_liquidado":80.5,"pct_pago":58.2},{"funcao":"DESPORTO E LAZER","empenhado":3304439.42,"liquidado":1383249.79,"pago":1283678.56,"pct_liquidado":41.9,"pct_pago":38.8},{"funcao":"SANEAMENTO","empenhado":1945982.84,"liquidado":325048.22,"pago":325048.22,"pct_liquidado":16.7,"pct_pago":16.7},{"funcao":"CULTURA","empenhado":1645683.76,"liquidado":997448.21,"pago":852569.21,"pct_liquidado":60.6,"pct_pago":51.8},{"funcao":"HABITAÇÃO","empenhado":759507.26,"liquidado":340827.26,"pago":263272.28,"pct_liquidado":44.9,"pct_pago":34.7},{"funcao":"GESTÃO AMBIENTAL","empenhado":530623.45,"liquidado":453044.8,"pago":296070.89,"pct_liquidado":85.4,"pct_pago":55.8},{"funcao":"TRABALHO","empenhado":346150.0,"liquidado":344650.0,"pago":343900.0,"pct_liquidado":99.6,"pct_pago":99.3},{"funcao":"AGRICULTURA","empenhado":328909.91,"liquidado":306912.87,"pago":225475.91,"pct_liquidado":93.3,"pct_pago":68.6}]}}