{"municipio":"Ubatuba","anos":{"2020":null,"2021":{"empenhado":565842012.71,"liquidado":431472295.87,"pago":414973325.67,"pct_liquidado":76.3,"pct_pago":73.3,"variacao_pct":null},"2022":{"empenhado":668646843.04,"liquidado":533897193.42,"pago":516750790.71,"pct_liquidado":79.8,"pct_pago":77.3,"variacao_pct":18.2},"2023":{"empenhado":765126986.64,"liquidado":585953288.59,"pago":572821501.93,"pct_liquidado":76.6,"pct_pago":74.9,"variacao_pct":14.4},"2024":{"empenhado":1079442698.9,"liquidado":702907566.83,"pago":668061308.4,"pct_liquidado":65.1,"pct_pago":61.9,"variacao_pct":41.1},"2025":{"empenhado":1053778908.07,"liquidado":812919641.5,"pago":763520077.17,"pct_liquidado":77.1,"pct_pago":72.5,"variacao_pct":-2.4},"2026":{"empenhado":807145807.85,"liquidado":285458032.04,"pago":235173183.33,"pct_liquidado":35.4,"pct_pago":29.1,"variacao_pct":-23.4}}}